Workbook

Sheet README
A1: India environment startups: top 20 and WIPO patent matching
A2: Prepared 19 Oct 2026. Funding figures are secondary-source (aggregator) data and must be re-verified before publication.
A4: SHEETS
A5: Top20: ranked list with startup-level details (Deliverable 1.iii).
A6: Longlist_Exclusions: candidates considered but excluded, with reasons, plus next in line (supports Deliverable 1.ii).
A7: Aliases: applicant-name strings used to match WIPO records to companies (Deliverable 2.iii). Edit this sheet.
A8: WIPO_Raw: paste raw PATENTSCOPE export here (Deliverable 2.i). Column L matches each record to a company automatically.
A9: Patent_Summary: WIPO counts merged with Top20 details. Updates automatically from WIPO_Raw (Deliverable 2.ii).
A10: Sources: where every number came from.
A12: STATUS: WHAT IS DONE AND WHAT IS NOT
A13: DONE: top-20 list, ranking, startup details, exclusion log, alias table, matching formulas.
A14: NOT DONE: the WIPO raw download. It could not be run from this environment (no direct access to PATENTSCOPE). WIPO_Raw is an empty template, so Patent_Summary shows zeros until you paste data.
... A22: COLOUR LEGEND: blue text = hardcoded input from a source; black = formula; yellow fill = cell you should fill in.

Sheet Top20
A1: Top 20 environment / climate-tech startups in India, ranked by total disclosed funding
A2: Funding in USD millions, equity plus debt as reported by the source. Ranking rule and exclusions are in Longlist_Exclusions and the Word document.
A4: Rank | B4: Company | C4: Segment | D4: Founded | E4: HQ | F4: Founders (as listed) | G4: Total funding (USD M) | H4: Last funding stage | I4: Employees (approx.) | J4: Company type | K4: Eligibility flag | L4: Primary source | M4: Verify before use
A5: =RANK(G5,$G$5:$G$24) -> 1 | B5: Greenko Group | C5: Renewable power and storage | D5: 2009 | E5: Hyderabad | F5: Anil Chalamalasetty, Mahesh Kolli | G5: 6700 | H5: n/a | I5: n/a | J5: Infrastructure / IPP (debt-heavy) | K5: Check ownership change | L5: S2 | M5: Founded year and founders from general knowledge, not the source. Figure is an older Inc42 article.
A6: =RANK(G6,$G$5:$G$24) -> 2 | B6: Avaada Group | C6: Renewable power, green hydrogen, solar manufacturing | D6: 2017 | E6: New Delhi | F6: Vineet Mittal | G6: 3700 | H6: Undisclosed | I6: 2,268 | J6: Infrastructure / IPP (debt-heavy) | L6: S3 | M6: Another aggregator shows $469.8M; the gap is likely debt and project finance. Founders from general knowledge.
A7: =RANK(G7,$G$5:$G$24) -> 3 | B7: EV Co | C7: Electric vehicles (entity unclear) | D7: 2022 | E7: Verify | F7: Vinod Philips | G7: 463.86 | H7: Undisclosed | I7: n/a | J7: Startup | K7: Identity unclear | L7: S1 | M7: Confirm which operating company this record refers to before searching patents.
A8: =RANK(G8,$G$5:$G$24) -> 4 | B8: Euler Motors | C8: Electric commercial three-wheelers | D8: 2018 | E8: New Delhi | F8: Saurav Kumar | G8: 376.94 | H8: Series E | I8: 1,588 | J8: Startup | L8: S1
A9: =RANK(G9,$G$5:$G$24) -> 5 | B9: Simple Energy | C9: Electric two-wheelers | D9: 2019 | E9: Bengaluru | F9: Hrishikesh Bhargava +4 | G9: 290.5 | H9: Series C | I9: 673 | J9: Startup | L9: S1 | M9: A Rs 1,750 crore Series C was reported on 30 Sep 2026 (S5); check it is in the figure.
A10: =RANK(G10,$G$5:$G$24) -> 6 | B10: Bounce | C10: Electric mobility and battery swapping | D10: 2014 | E10: Bengaluru | F10: Anil G +2 | G10: 238.06 | H10: Undisclosed | I10: 637 | J10: Startup | K10: Generic name | L10: S1 | M10: Legal entity name needed; brand is a common word.
A11: =RANK(G11,$G$5:$G$24) -> 7 | B11: Battery Smart | C11: Battery swapping | D11: 2019 | E11: New Delhi | F11: Pulkit Khurana +1 | G11: 228.09 | H11: Debt | I11: 1,155 | J11: Startup | L11: S1 | M11: Another source shows $192M (S5).
A12: =RANK(G12,$G$5:$G$24) -> 8 | B12: Ultraviolette Automotive | C12: Electric motorcycles | D12: 2016 | E12: Bengaluru | F12: Narayan Subramaniam +1 | G12: 220.9 | H12: Series E | I12: 586 | J12: Startup | L12: S1 | M12: An $85M round was reported Sep 2026 (S5); check it is in the figure.
A13: =RANK(G13,$G$5:$G$24) -> 9 | B13: Carbon Clean Solutions | C13: Carbon capture | D13: 2009 | E13: London (UK); India operations | F13: Aniruddha Sharma +1 | G13: 190.61 | H13: Series C | I13: 188 | J13: Startup | K13: Borderline: HQ outside India | L13: S1 | M13: Indian origin but UK headquarters; confirm eligibility under your own definition.
A14: =RANK(G14,$G$5:$G$24) -> 10 | B14: CleanMax | C14: Commercial and industrial solar | D14: 2010 | E14: Mumbai | F14: Kuldeep Jain | G14: 188.2 | H14: n/a | I14: n/a | J14: Infrastructure / IPP (debt-heavy) | L14: S4 | M14: Older Inc42 figure; refresh. Founded year and founder from general knowledge.
A15: =RANK(G15,$G$5:$G$24) -> 11 | B15: River | C15: Electric scooters | D15: 2020 | E15: Bengaluru | F15: Aravind Mani +1 | G15: 188 | H15: Series C | I15: 1,174 | J15: Startup | K15: Generic name | L15: S1 | M15: Legal entity name needed.
A16: =RANK(G16,$G$5:$G$24) -> 12 | B16: SUN Mobility | C16: Battery swapping and energy infrastructure | D16: 2017 | E16: Bengaluru | F16: Ajay Goel +2 | G16: 135 | H16: Undisclosed | I16: 959 | J16: Startup | L16: S1 | M16: Another source shows $50M (S6); older.
A17: =RANK(G17,$G$5:$G$24) -> 13 | B17: SolarSquare | C17: Rooftop solar | D17: 2015 | E17: Mumbai | F17: Shreya Mishra +2 | G17: 113.25 | H17: Undisclosed | I17: 2,924 | J17: Startup | L17: S1
A18: =RANK(G18,$G$5:$G$24) -> 14 | B18: Ecozen Solutions | C18: Solar cold chain and agri-energy | D18: 2010 | E18: Pune | F18: Devendra Gupta +2 | G18: 107.4 | H18: Debt | I18: 620 | J18: Startup | L18: S1 | M18: Another source shows $104M (S5).
A19: =RANK(G19,$G$5:$G$24) -> 15 | B19: EKA Mobility | C19: Electric buses and commercial EVs | D19: 2022 | E19: Pune | F19: Sudhir Mehta | G19: 103.94 | H19: Undisclosed | I19: 1,113 | J19: Startup | K19: Group-backed | L19: S1 | M19: Promoter-backed; confirm it meets your startup definition.
A20: =RANK(G20,$G$5:$G$24) -> 16 | B20: Bidgely | C20: Energy analytics software | D20: 2011 | E20: Los Altos (US); Bengaluru operations | F20: Abhay Gupta +1 | G20: 97.67 | H20: Undisclosed | I20: 277 | J20: Startup | K20: Borderline: HQ outside India | L20: S1 | M20: Confirm eligibility.
A21: =RANK(G21,$G$5:$G$24) -> 17 | B21: Matter | C21: Electric motorcycles and batteries | D21: 2019 | E21: Ahmedabad | F21: Arun Pratap Singh +3 | G21: 88 | H21: Undisclosed | I21: 754 | J21: Startup | K21: Generic name | L21: S1 | M21: Legal entity name needed.
A22: =RANK(G22,$G$5:$G$24) -> 18 | B22: ChargeZone | C22: EV charging | D22: 2018 | E22: Verify | F22: Kartikey Hariyani | G22: 86.11 | H22: Venture round | I22: 213 | J22: Startup | L22: S1
A23: =RANK(G23,$G$5:$G$24) -> 19 | B23: Twenty Two Motors | C23: Electric two-wheelers | D23: 2016 | E23: Verify | F23: Parveen Kharb +1 | G23: 66.6 | H23: Corporate round | I23: 19 | J23: Startup | L23: S1 | M23: Employee count looks low against funding; confirm.
A24: =RANK(G24,$G$5:$G$24) -> 20 | B24: Exponent Energy | C24: Fast-charging batteries and charging | D24: 2020 | E24: Bengaluru | F24: Arun Vinayak +1 | G24: 65.41 | H24: Undisclosed | I24: 334 | J24: Startup | L24: S1
B26: Total, all 20 | G26: =SUM(G5:G24) -> 13648.54
B27: Total, VC-style startups only (excludes Infrastructure / IPP) | G27: =SUMIF(J5:J24,"Startup",G5:G24) -> 3060.34
B28: Share of total held by Infrastructure / IPP | G28: =1-G27/G26 -> 0.77577528
B30: Source codes S1-S6 are listed on the Sources sheet. Blue = hardcoded from source.

Sheet Longlist_Exclusions
A1: Candidates considered but not in the top 20, and next in line
A2: Ranking rule: total disclosed funding (USD), after applying the inclusion tests in the Word document, section 2.
A4: Company | B4: Total funding (USD M) | C4: Decision | D4: Reason | E4: Source
A5: ReNew Energy | B5: 4380 | C5: Excluded | D5: Publicly listed company (Nasdaq). Verify current listing status. | E5: S1
A6: Ola Electric | B6: 1500 | C6: Excluded | D6: Publicly listed in India since 2024. | E6: S1
A7: ACME Solar | B7: 1250 | C7: Excluded | D7: Publicly listed in India since 2024; Inc42 shows post-IPO debt. | E7: S1
A8: Ather Energy | B8: 574.27 | C8: Excluded | D8: Publicly listed in India since 2025. | E8: S1
A9: Smartron | B9: 200 | C9: Excluded | D9: Classified Clean Tech by the source, but it is a consumer electronics and IoT business, outside the environment scope. | E9: S1
A10: Agratas | B10: 113.14 | C10: Excluded | D10: Battery arm of the Tata group; not an independent startup. | E10: S1
A11: Gensol Engineering | B11: 76.8 | C11: Excluded | D11: Listed company; the source classes it as an investor, not an operating startup. | E11: S1
A12: Recykal | B12: 60.19 | C12: Next in line (rank 21) | D12: Waste and recycling marketplace. Would enter the top 20 if either borderline-HQ company (Carbon Clean, Bidgely) is dropped. | E12: S1
A13: Inox Clean Energy | C13: Not ranked | D13: A $344M Series D was reported in 2026, but no cumulative total was retrieved and it appears to be group-owned. Verify. | E13: S5
A14: Radiance Renewables | C14: Not ranked | D14: A $100M round was reported in Feb 2026; cumulative total not retrieved. Verify. | E14: S7

Sheet Aliases
A1: Applicant-name strings used for matching (edit me)
A2: Each row is searched as a substring (case-insensitive) inside the WIPO applicant field. Column B must equal the company name on Top20 exactly. Add legal entity names after checking MCA21.
A4: Alias (search string) | B4: Company (must match Top20) | C4: Basis | D4: False-positive risk | E4: Notes
A5: Greenko | B5: Greenko Group | C5: Brand | D5: Low | E5: Group has many subsidiaries; capture legal entity names.
A6: Avaada | B6: Avaada Group | C6: Brand | D6: Low | E6: Several Avaada Pvt Ltd entities.
A7: EV Co | B7: EV Co | C7: Brand | D7: High | E7: Very generic. Do not use until the legal entity is confirmed.
A8: Euler Motors | B8: Euler Motors | C8: Brand | D8: Low
A9: Simple Energy | B9: Simple Energy | C9: Brand | D9: Medium | E9: Common phrase; review every hit.
A10: Bounce | B10: Bounce | C10: Brand | D10: High | E10: Common word; use legal entity name instead.
A11: Battery Smart | B11: Battery Smart | C11: Brand | D11: Medium
A12: BatterySmart | B12: Battery Smart | C12: Spelling variant | D12: Medium
A13: Ultraviolette | B13: Ultraviolette Automotive | C13: Brand | D13: Low
A14: Carbon Clean | B14: Carbon Clean Solutions | C14: Brand | D14: Medium | E14: Files under the UK entity as well.
A15: CleanMax | B15: CleanMax | C15: Brand | D15: Low
A16: River Mobility | B16: River | C16: Working legal name | D16: Medium | E16: Confirm legal name; plain 'River' would create many false hits.
A17: SUN Mobility | B17: SUN Mobility | C17: Brand | D17: Medium
A18: SolarSquare | B18: SolarSquare | C18: Brand | D18: Low
A19: Solar Square | B19: SolarSquare | C19: Spelling variant | D19: Medium
A20: Ecozen | B20: Ecozen Solutions | C20: Brand | D20: Low
A21: Eka Mobility | B21: EKA Mobility | C21: Brand | D21: Low
A22: Bidgely | B22: Bidgely | C22: Brand | D22: Low | E22: Mostly files as a US entity.
A23: Matter Motor Works | B23: Matter | C23: Working legal name | D23: Medium | E23: Confirm legal name on MCA21.
A24: ChargeZone | B24: ChargeZone | C24: Brand | D24: Low
A25: Charge Zone | B25: ChargeZone | C25: Spelling variant | D25: Medium
A26: Twenty Two Motors | B26: Twenty Two Motors | C26: Brand | D26: Low
A27: Exponent Energy | B27: Exponent Energy | C27: Brand | D27: Low

Sheet Patent_Summary
A1: WIPO patent records merged with startup details
A2: Counts exclude records you mark 'False positive'. All cells are formulas; they fill in once WIPO_Raw has data.
A4: Rank | B4: Company | C4: Segment | D4: Founded | E4: Total funding (USD M) | F4: Patent records (matched) | G4: Granted | H4: Filed (not granted) | I4: Patents per USD 100M funding | J4: Records pending review
A5: ='Top20'!A5 -> 1 | B5: ='Top20'!B5 -> Greenko Group | C5: ='Top20'!C5 -> Renewable power and storage | D5: ='Top20'!D5 -> 2009 | E5: ='Top20'!G5 -> 6700 | F5: =COUNTIFS(WIPO_Raw!$L$5:$L$2004,B5,WIPO_Raw!$M$5:$M$2004,"<>False positive") -> 0 | G5: =COUNTIFS(WIPO_Raw!$L$5:$L$2004,B5,WIPO_Raw!$M$5:$M$2004,"<>False positive",WIPO_Raw!$K$5:$K$2004,"Granted") -> 0 | H5: =F5-G5 -> 0 | I5: =IFERROR(F5/(E5/100),0) -> 0 | J5: =COUNTIFS(WIPO_Raw!$L$5:$L$2004,B5,WIPO_Raw!$M$5:$M$2004,"") -> 0
A6: ='Top20'!A6 -> 2 | B6: ='Top20'!B6 -> Avaada Group | C6: ='Top20'!C6 -> Renewable power, green hydrogen, solar manufacturing | D6: ='Top20'!D6 -> 2017 | E6: ='Top20'!G6 -> 3700 | F6: =COUNTIFS(WIPO_Raw!$L$5:$L$2004,B6,WIPO_Raw!$M$5:$M$2004,"<>False positive") -> 0 | G6: =COUNTIFS(WIPO_Raw!$L$5:$L$2004,B6,WIPO_Raw!$M$5:$M$2004,"<>False positive",WIPO_Raw!$K$5:$K$2004,"Granted") -> 0 | H6: =F6-G6 -> 0 | I6: =IFERROR(F6/(E6/100),0) -> 0 | J6: =COUNTIFS(WIPO_Raw!$L$5:$L$2004,B6,WIPO_Raw!$M$5:$M$2004,"") -> 0
A7: ='Top20'!A7 -> 3 | B7: ='Top20'!B7 -> EV Co | C7: ='Top20'!C7 -> Electric vehicles (entity unclear) | D7: ='Top20'!D7 -> 2022 | E7: ='Top20'!G7 -> 463.86 | F7: =COUNTIFS(WIPO_Raw!$L$5:$L$2004,B7,WIPO_Raw!$M$5:$M$2004,"<>False positive") -> 0 | G7: =COUNTIFS(WIPO_Raw!$L$5:$L$2004,B7,WIPO_Raw!$M$5:$M$2004,"<>False positive",WIPO_Raw!$K$5:$K$2004,"Granted") -> 0 | H7: =F7-G7 -> 0 | I7: =IFERROR(F7/(E7/100),0) -> 0 | J7: =COUNTIFS(WIPO_Raw!$L$5:$L$2004,B7,WIPO_Raw!$M$5:$M$2004,"") -> 0
A8: ='Top20'!A8 -> 4 | B8: ='Top20'!B8 -> Euler Motors | C8: ='Top20'!C8 -> Electric commercial three-wheelers | D8: ='Top20'!D8 -> 2018 | E8: ='Top20'!G8 -> 376.94 | F8: =COUNTIFS(WIPO_Raw!$L$5:$L$2004,B8,WIPO_Raw!$M$5:$M$2004,"<>False positive") -> 0 | G8: =COUNTIFS(WIPO_Raw!$L$5:$L$2004,B8,WIPO_Raw!$M$5:$M$2004,"<>False positive",WIPO_Raw!$K$5:$K$2004,"Granted") -> 0 | H8: =F8-G8 -> 0 | I8: =IFERROR(F8/(E8/100),0) -> 0 | J8: =COUNTIFS(WIPO_Raw!$L$5:$L$2004,B8,WIPO_Raw!$M$5:$M$2004,"") -> 0
A9: ='Top20'!A9 -> 5 | B9: ='Top20'!B9 -> Simple Energy | C9: ='Top20'!C9 -> Electric two-wheelers | D9: ='Top20'!D9 -> 2019 | E9: ='Top20'!G9 -> 290.5 | F9: =COUNTIFS(WIPO_Raw!$L$5:$L$2004,B9,WIPO_Raw!$M$5:$M$2004,"<>False positive") -> 0 | G9: =COUNTIFS(WIPO_Raw!$L$5:$L$2004,B9,WIPO_Raw!$M$5:$M$2004,"<>False positive",WIPO_Raw!$K$5:$K$2004,"Granted") -> 0 | H9: =F9-G9 -> 0 | I9: =IFERROR(F9/(E9/100),0) -> 0 | J9: =COUNTIFS(WIPO_Raw!$L$5:$L$2004,B9,WIPO_Raw!$M$5:$M$2004,"") -> 0
A10: ='Top20'!A10 -> 6 | B10: ='Top20'!B10 -> Bounce | C10: ='Top20'!C10 -> Electric mobility and battery swapping | D10: ='Top20'!D10 -> 2014 | E10: ='Top20'!G10 -> 238.06 | F10: =COUNTIFS(WIPO_Raw!$L$5:$L$2004,B10,WIPO_Raw!$M$5:$M$2004,"<>False positive") -> 0 | G10: =COUNTIFS(WIPO_Raw!$L$5:$L$2004,B10,WIPO_Raw!$M$5:$M$2004,"<>False positive",WIPO_Raw!$K$5:$K$2004,"Granted") -> 0 | H10: =F10-G10 -> 0 | I10: =IFERROR(F10/(E10/100),0) -> 0 | J10: =COUNTIFS(WIPO_Raw!$L$5:$L$2004,B10,WIPO_Raw!$M$5:$M$2004,"") -> 0
A11: ='Top20'!A11 -> 7 | B11: ='Top20'!B11 -> Battery Smart | C11: ='Top20'!C11 -> Battery swapping | D11: ='Top20'!D11 -> 2019 | E11: ='Top20'!G11 -> 228.09 | F11: =COUNTIFS(WIPO_Raw!$L$5:$L$2004,B11,WIPO_Raw!$M$5:$M$2004,"<>False positive") -> 0 | G11: =COUNTIFS(WIPO_Raw!$L$5:$L$2004,B11,WIPO_Raw!$M$5:$M$2004,"<>False positive",WIPO_Raw!$K$5:$K$2004,"Granted") -> 0 | H11: =F11-G11 -> 0 | I11: =IFERROR(F11/(E11/100),0) -> 0 | J11: =COUNTIFS(WIPO_Raw!$L$5:$L$2004,B11,WIPO_Raw!$M$5:$M$2004,"") -> 0
A12: ='Top20'!A12 -> 8 | B12: ='Top20'!B12 -> Ultraviolette Automotive | C12: ='Top20'!C12 -> Electric motorcycles | D12: ='Top20'!D12 -> 2016 | E12: ='Top20'!G12 -> 220.9 | F12: =COUNTIFS(WIPO_Raw!$L$5:$L$2004,B12,WIPO_Raw!$M$5:$M$2004,"<>False positive") -> 0 | G12: =COUNTIFS(WIPO_Raw!$L$5:$L$2004,B12,WIPO_Raw!$M$5:$M$2004,"<>False positive",WIPO_Raw!$K$5:$K$2004,"Granted") -> 0 | H12: =F12-G12 -> 0 | I12: =IFERROR(F12/(E12/100),0) -> 0 | J12: =COUNTIFS(WIPO_Raw!$L$5:$L$2004,B12,WIPO_Raw!$M$5:$M$2004,"") -> 0
A13: ='Top20'!A13 -> 9 | B13: ='Top20'!B13 -> Carbon Clean Solutions | C13: ='Top20'!C13 -> Carbon capture | D13: ='Top20'!D13 -> 2009 | E13: ='Top20'!G13 -> 190.61 | F13: =COUNTIFS(WIPO_Raw!$L$5:$L$2004,B13,WIPO_Raw!$M$5:$M$2004,"<>False positive") -> 0 | G13: =COUNTIFS(WIPO_Raw!$L$5:$L$2004,B13,WIPO_Raw!$M$5:$M$2004,"<>False positive",WIPO_Raw!$K$5:$K$2004,"Granted") -> 0 | H13: =F13-G13 -> 0 | I13: =IFERROR(F13/(E13/100),0) -> 0 | J13: =COUNTIFS(WIPO_Raw!$L$5:$L$2004,B13,WIPO_Raw!$M$5:$M$2004,"") -> 0
A14: ='Top20'!A14 -> 10 | B14: ='Top20'!B14 -> CleanMax | C14: ='Top20'!C14 -> Commercial and industrial solar | D14: ='Top20'!D14 -> 2010 | E14: ='Top20'!G14 -> 188.2 | F14: =COUNTIFS(WIPO_Raw!$L$5:$L$2004,B14,WIPO_Raw!$M$5:$M$2004,"<>False positive") -> 0 | G14: =COUNTIFS(WIPO_Raw!$L$5:$L$2004,B14,WIPO_Raw!$M$5:$M$2004,"<>False positive",WIPO_Raw!$K$5:$K$2004,"Granted") -> 0 | H14: =F14-G14 -> 0 | I14: =IFERROR(F14/(E14/100),0) -> 0 | J14: =COUNTIFS(WIPO_Raw!$L$5:$L$2004,B14,WIPO_Raw!$M$5:$M$2004,"") -> 0
A15: ='Top20'!A15 -> 11 | B15: ='Top20'!B15 -> River | C15: ='Top20'!C15 -> Electric scooters | D15: ='Top20'!D15 -> 2020 | E15: ='Top20'!G15 -> 188 | F15: =COUNTIFS(WIPO_Raw!$L$5:$L$2004,B15,WIPO_Raw!$M$5:$M$2004,"<>False positive") -> 0 | G15: =COUNTIFS(WIPO_Raw!$L$5:$L$2004,B15,WIPO_Raw!$M$5:$M$2004,"<>False positive",WIPO_Raw!$K$5:$K$2004,"Granted") -> 0 | H15: =F15-G15 -> 0 | I15: =IFERROR(F15/(E15/100),0) -> 0 | J15: =COUNTIFS(WIPO_Raw!$L$5:$L$2004,B15,WIPO_Raw!$M$5:$M$2004,"") -> 0
A16: ='Top20'!A16 -> 12 | B16: ='Top20'!B16 -> SUN Mobility | C16: ='Top20'!C16 -> Battery swapping and energy infrastructure | D16: ='Top20'!D16 -> 2017 | E16: ='Top20'!G16 -> 135 | F16: =COUNTIFS(WIPO_Raw!$L$5:$L$2004,B16,WIPO_Raw!$M$5:$M$2004,"<>False positive") -> 0 | G16: =COUNTIFS(WIPO_Raw!$L$5:$L$2004,B16,WIPO_Raw!$M$5:$M$2004,"<>False positive",WIPO_Raw!$K$5:$K$2004,"Granted") -> 0 | H16: =F16-G16 -> 0 | I16: =IFERROR(F16/(E16/100),0) -> 0 | J16: =COUNTIFS(WIPO_Raw!$L$5:$L$2004,B16,WIPO_Raw!$M$5:$M$2004,"") -> 0
... A24: ='Top20'!A24 -> 20 | B24: ='Top20'!B24 -> Exponent Energy | C24: ='Top20'!C24 -> Fast-charging batteries and charging | D24: ='Top20'!D24 -> 2020 | E24: ='Top20'!G24 -> 65.41 | F24: =COUNTIFS(WIPO_Raw!$L$5:$L$2004,B24,WIPO_Raw!$M$5:$M$2004,"<>False positive") -> 0 | G24: =COUNTIFS(WIPO_Raw!$L$5:$L$2004,B24,WIPO_Raw!$M$5:$M$2004,"<>False positive",WIPO_Raw!$K$5:$K$2004,"Granted") -> 0 | H24: =F24-G24 -> 0 | I24: =IFERROR(F24/(E24/100),0) -> 0 | J24: =COUNTIFS(WIPO_Raw!$L$5:$L$2004,B24,WIPO_Raw!$M$5:$M$2004,"") -> 0
B26: Total matched | F26: =SUM(F5:F24) -> 0 | G26: =SUM(G5:G24) -> 0 | H26: =SUM(H5:H24) -> 0 | J26: =SUM(J5:J24) -> 0
B27: Records with no company match (UNMATCHED) | F27: =COUNTIF(WIPO_Raw!$L$5:$L$2004,"UNMATCHED") -> 0
B28: Total records in WIPO_Raw | F28: =COUNTA(WIPO_Raw!$E$5:$E$2004) -> 0
B29: Check: matched + unmatched = total (should be 0) | F29: =F28-COUNTIF(WIPO_Raw!$L$5:$L$2004,"?*") -> 0
B31: Green text = linked from Top20. 'False positive' records are removed from counts but stay in WIPO_Raw for audit.

Sheet Sources
A1: Sources
A3: Code | B3: Source | C3: URL | D3: What it supplied
A4: S1 | B4: Inc42 Datalabs, Top 30 Funded Cleantech Startups in India 2026 | C4: https://inc42.com/lists/top-30-funded-cleantech-startups-in-india-2026/ | D4: Ranked funding, founded year, founders, last stage, employees for ranks 3-20 and exclusions
A5: S2 | B5: Inc42, 7 Cleantech Startups Promoting Sustainable Lifestyle in India | C5: https://inc42.com/?p=438230 | D5: Greenko and CleanMax total funding (older figures)
A6: S3 | B6: Inc42 company page, Avaada | C6: https://inc42.com/company/avaada/funding/ | D6: Avaada total funding $3.70B+ as of Jan 2025
A7: S4 | B7: Inc42 article cited in S2 | C7: https://inc42.com/?p=438230 | D7: CleanMax $188.2M
A8: S5 | B8: Best Startup India, climate tech articles (2026) | C8: https://beststartup.in/climate-tech-startups-india-2026/ | D8: Cross-check figures (Battery Smart, Ecozen), recent rounds (Simple Energy, Ultraviolette, Inox Clean Energy)
A9: S6 | B9: Inc42 web story, 10 most funded EV startups | C9: https://inc42.com/web-stories/10-most-funded-ev-startups-of-india | D9: Older SUN Mobility figure for comparison
A10: S7 | B10: Entrepreneur India weekly wrap, Feb 2026 | C10: https://india.entrepreneur.com/news-and-trends/weekly-wrap-major-deals-strategic-acquisitions-and-ipo/502706 | D10: Radiance Renewables $100M round
A11: S8 | B11: Tracxn India Climate Tech 2026 report (press coverage) | C11: https://www.downtoearth.org.in/energy/indias-climate-tech-funding-reaches-128-bn-as-energy-security-concerns-drive-investment-surge | D11: Sector totals: $12.8B across 1,583 companies

Sheet WIPO_Raw
A1: WIPO PATENTSCOPE raw export (paste here)
A2: Paste export rows into columns A-J from row 5. Columns K and M are typed by you. Column L is a formula (rows 5-2004). Column names follow the PATENTSCOPE export; rename to match your file if needed.
A4: Publication number | B4: Publication date | C4: Application number | D4: Filing date | E4: Applicant(s) | F4: Inventor(s) | G4: Title | H4: IPC | I4: Office / country | J4: Kind code | K4: Status (Filed / Granted) | L4: Matched company (formula) | M4: Review (Confirmed / False positive) | N4: Match note
L5: =IF(E5="","",IFERROR(INDEX(Aliases!$B$5:$B$80,MATCH(1,INDEX(ISNUMBER(SEARCH(Aliases!$A$5:$A$80,E5))*(Aliases!$A$5:$A$80<>""),0),0)),"UNMATCHED"))
L6: =IF(E6="","",IFERROR(INDEX(Aliases!$B$5:$B$80,MATCH(1,INDEX(ISNUMBER(SEARCH(Aliases!$A$5:$A$80,E6))*(Aliases!$A$5:$A$80<>""),0),0)),"UNMATCHED"))
L7: =IF(E7="","",IFERROR(INDEX(Aliases!$B$5:$B$80,MATCH(1,INDEX(ISNUMBER(SEARCH(Aliases!$A$5:$A$80,E7))*(Aliases!$A$5:$A$80<>""),0),0)),"UNMATCHED"))
L8: =IF(E8="","",IFERROR(INDEX(Aliases!$B$5:$B$80,MATCH(1,INDEX(ISNUMBER(SEARCH(Aliases!$A$5:$A$80,E8))*(Aliases!$A$5:$A$80<>""),0),0)),"UNMATCHED"))
L9: =IF(E9="","",IFERROR(INDEX(Aliases!$B$5:$B$80,MATCH(1,INDEX(ISNUMBER(SEARCH(Aliases!$A$5:$A$80,E9))*(Aliases!$A$5:$A$80<>""),0),0)),"UNMATCHED"))
L10: =IF(E10="","",IFERROR(INDEX(Aliases!$B$5:$B$80,MATCH(1,INDEX(ISNUMBER(SEARCH(Aliases!$A$5:$A$80,E10))*(Aliases!$A$5:$A$80<>""),0),0)),"UNMATCHED"))
L11: =IF(E11="","",IFERROR(INDEX(Aliases!$B$5:$B$80,MATCH(1,INDEX(ISNUMBER(SEARCH(Aliases!$A$5:$A$80,E11))*(Aliases!$A$5:$A$80<>""),0),0)),"UNMATCHED"))
L12: =IF(E12="","",IFERROR(INDEX(Aliases!$B$5:$B$80,MATCH(1,INDEX(ISNUMBER(SEARCH(Aliases!$A$5:$A$80,E12))*(Aliases!$A$5:$A$80<>""),0),0)),"UNMATCHED"))
L13: =IF(E13="","",IFERROR(INDEX(Aliases!$B$5:$B$80,MATCH(1,INDEX(ISNUMBER(SEARCH(Aliases!$A$5:$A$80,E13))*(Aliases!$A$5:$A$80<>""),0),0)),"UNMATCHED"))
L14: =IF(E14="","",IFERROR(INDEX(Aliases!$B$5:$B$80,MATCH(1,INDEX(ISNUMBER(SEARCH(Aliases!$A$5:$A$80,E14))*(Aliases!$A$5:$A$80<>""),0),0)),"UNMATCHED"))
L15: =IF(E15="","",IFERROR(INDEX(Aliases!$B$5:$B$80,MATCH(1,INDEX(ISNUMBER(SEARCH(Aliases!$A$5:$A$80,E15))*(Aliases!$A$5:$A$80<>""),0),0)),"UNMATCHED"))
L16: =IF(E16="","",IFERROR(INDEX(Aliases!$B$5:$B$80,MATCH(1,INDEX(ISNUMBER(SEARCH(Aliases!$A$5:$A$80,E16))*(Aliases!$A$5:$A$80<>""),0),0)),"UNMATCHED"))
... L2004: =IF(E2004="","",IFERROR(INDEX(Aliases!$B$5:$B$80,MATCH(1,INDEX(ISNUMBER(SEARCH(Aliases!$A$5:$A$80,E2004))*(Aliases!$A$5:$A$80<>""),0),0)),"UNMATCHED"))
